decoder.v
module decoder(input clk, input A, input B, input reset, output reg[7:0] count);

    reg [1:0] state;
    parameter A_LEAD = 2'b00, B_LEAD = 2'b01, NO_SIG = 2'b10;
    reg[7:0] counter = 0;

    reg a_high, b_high;

    always @(posedge clk or negedge reset) begin
        if(reset) state <= NO_SIG;
        count <= counter;
    end

    always @(posedge clk) begin
        if(A) a_high<= 1;
        else a_high <= 0;
    end
    
    always @(posedge clk) begin
        if(B) b_high <= 1;
        else b_high <= 0;
    end

    always @(*) begin
        case(state)
            A_LEAD: begin 
                case({a_high, b_high})
                    2'b00: state <= NO_SIG;
                    2'b11: state <= A_LEAD;
                endcase
            end
            B_LEAD: begin 
                case({a_high, b_high})
                    2'b00: state <= NO_SIG;
                    default: state <= B_LEAD;
                endcase
            end
            NO_SIG: begin
                case({a_high, b_high})
                    2'b10: begin
                        state <= A_LEAD;
                        counter--;
                    end
                    2'b01: begin
                        state <= B_LEAD;
                        counter++;
                    end
                    default: state <= NO_SIG;
                endcase
            end
        endcase
    end

    // always @(posedge clk) begin
    //     case(state)
    //         A_LEAD: counter--;
    //         B_LEAD: counter++;
    //         default: count <= count;
    //     endcase
    // end

endmodule

quad.v
module quad(input clk, input dir, input reset, output reg A, output reg B);

    parameter PULSE_WIDTH = 2;
    reg[9:0] clk_count=0;
    reg width_clk=0;

    parameter UP0 = 3'b000, UP1 = 3'b001, UP2 = 3'b010, UP3 = 3'b011;
    parameter DOWN0 = 3'b100, DOWN1 = 3'b101, DOWN2 = 3'b110, DOWN3 = 3'b111;
    reg[2:0] state, next_state;

    always @(posedge clk) begin
        if(clk_count < (PULSE_WIDTH-1)/2) clk_count <= clk_count + 1;
        else begin
            clk_count <= 0;
            width_clk <= ~width_clk;
        end
    end

    always @(posedge clk) begin
        case(state)
            UP0: next_state <= (dir==1)? DOWN0:UP1;
            UP1: next_state <= (dir==1)? DOWN0:UP2;
            UP2: next_state <= (dir==1)? DOWN0:UP3;
            UP3: next_state <= (dir==1)? DOWN0:UP0;
            DOWN0: next_state <= (dir==1)? UP0:DOWN1;
            DOWN1: next_state <= (dir==1)? UP0:DOWN2;
            DOWN2: next_state <= (dir==1)? UP0:DOWN3;
            DOWN3: next_state <= (dir==1)? UP0:DOWN0;
        endcase
    end

    always @(posedge width_clk, posedge reset) begin
        if(reset) state <= UP0;
        else state <= next_state;
    end


    always @(posedge width_clk) begin
        case(state)
            UP0: begin
                A <= 0;
                B <= 0;
            end
            UP1: begin
                A <= 0;
                B <= 1;
            end
            UP2: begin
                A <= 1;
                B <= 1;
            end
            UP3: begin
                A <= 1;
                B <= 0;
            end
            DOWN0: begin
                A <= 0;
                B <= 0;
            end
            DOWN1: begin
                A <= 1;
                B <= 0;
            end
            DOWN2: begin
                A <= 1;
                B <= 1;
            end
            DOWN3: begin
                A <= 0;
                B <= 1;
            end
        endcase
    end
    

endmodule

tb_quad.v
`include "quad.v"
`include "decoder.v"
module tb_quad;

reg clk, dir, reset;
wire[7:0] count;
wire A, B;

quad enc(clk, dir, reset, A, B);
decoder dec(clk, A, B, reset, count); 

initial begin
    $dumpfile("tb_quad.vcd");
    $dumpvars(0, tb_quad);
    clk = 0;
    forever #5 clk = ~clk;
end

initial begin
    reset = 1; dir = 0;
    #12 reset = 0;
    
    //#25 dir = 1; #10 dir = 0;
    #525 dir = 1; #10 dir = 0;
    #500 $finish;
end

endmodule

tb_quad.vcd
$date
	Wed Nov 20 21:40:00 2024
$end
$version
	Icarus Verilog
$end
$timescale
	1s
$end
$scope module tb_quad $end
$var wire 8 ! count [7:0] $end
$var wire 1 " B $end
$var wire 1 # A $end
$var reg 1 $ clk $end
$var reg 1 % dir $end
$var reg 1 & reset $end
$scope module dec $end
$var wire 1 $ clk $end
$var wire 1 & reset $end
$var wire 1 " B $end
$var wire 1 # A $end
$var reg 1 ' a_high $end
$var reg 1 ( b_high $end
$var reg 8 ) count [7:0] $end
$var reg 8 * counter [7:0] $end
$var reg 2 + state [1:0] $end
$upscope $end
$scope module enc $end
$var wire 1 $ clk $end
$var wire 1 % dir $end
$var wire 1 & reset $end
$var reg 1 # A $end
$var reg 1 " B $end
$var reg 10 , clk_count [9:0] $end
$var reg 3 - next_state [2:0] $end
$var reg 3 . state [2:0] $end
$var reg 1 / width_clk $end
$upscope $end
$upscope $end
$enddefinitions $end
#0
$dumpvars
0/
b0 .
bx -
b0 ,
bx +
b0 *
bx )
x(
x'
1&
0%
0$
x#
x"
bx !
$end
#5
0"
0#
1/
b1 -
0'
0(
b0 !
b0 )
b10 +
1$
#10
0$
#12
0&
#15
0/
1$
#20
0$
#25
b1 .
1/
1$
#30
0$
#35
b10 -
0/
1$
#40
0$
#45
1"
b10 .
1/
1$
#50
0$
#55
b1 +
b1 *
1(
b11 -
0/
1$
#60
0$
#65
1#
b11 .
1/
b1 !
b1 )
1$
#70
0$
#75
1'
b0 -
0/
1$
#80
0$
#85
0"
b0 .
1/
1$
#90
0$
#95
0(
b1 -
0/
1$
#100
0$
#105
0#
b1 .
1/
1$
#110
0$
#115
b10 +
0'
b10 -
0/
1$
#120
0$
#125
1"
b10 .
1/
1$
#130
0$
#135
b1 +
b10 *
1(
b11 -
0/
1$
#140
0$
#145
1#
b11 .
1/
b10 !
b10 )
1$
#150
0$
#155
1'
b0 -
0/
1$
#160
0$
#165
0"
b0 .
1/
1$
#170
0$
#175
0(
b1 -
0/
1$
#180
0$
#185
0#
b1 .
1/
1$
#190
0$
#195
b10 +
0'
b10 -
0/
1$
#200
0$
#205
1"
b10 .
1/
1$
#210
0$
#215
b1 +
b11 *
1(
b11 -
0/
1$
#220
0$
#225
1#
b11 .
1/
b11 !
b11 )
1$
#230
0$
#235
1'
b0 -
0/
1$
#240
0$
#245
0"
b0 .
1/
1$
#250
0$
#255
0(
b1 -
0/
1$
#260
0$
#265
0#
b1 .
1/
1$
#270
0$
#275
b10 +
0'
b10 -
0/
1$
#280
0$
#285
1"
b10 .
1/
1$
#290
0$
#295
b1 +
b100 *
1(
b11 -
0/
1$
#300
0$
#305
1#
b11 .
1/
b100 !
b100 )
1$
#310
0$
#315
1'
b0 -
0/
1$
#320
0$
#325
0"
b0 .
1/
1$
#330
0$
#335
0(
b1 -
0/
1$
#340
0$
#345
0#
b1 .
1/
1$
#350
0$
#355
b10 +
0'
b10 -
0/
1$
#360
0$
#365
1"
b10 .
1/
1$
#370
0$
#375
b1 +
b101 *
1(
b11 -
0/
1$
#380
0$
#385
1#
b11 .
1/
b101 !
b101 )
1$
#390
0$
#395
1'
b0 -
0/
1$
#400
0$
#405
0"
b0 .
1/
1$
#410
0$
#415
0(
b1 -
0/
1$
#420
0$
#425
0#
b1 .
1/
1$
#430
0$
#435
b10 +
0'
b10 -
0/
1$
#440
0$
#445
1"
b10 .
1/
1$
#450
0$
#455
b1 +
b110 *
1(
b11 -
0/
1$
#460
0$
#465
1#
b11 .
1/
b110 !
b110 )
1$
#470
0$
#475
1'
b0 -
0/
1$
#480
0$
#485
0"
b0 .
1/
1$
#490
0$
#495
0(
b1 -
0/
1$
#500
0$
#505
0#
b1 .
1/
1$
#510
0$
#515
b10 +
0'
b10 -
0/
1$
#520
0$
#525
1"
b10 .
1/
1$
#530
0$
#535
b1 +
b111 *
1(
b11 -
0/
1$
#537
1%
#540
0$
#545
1#
b100 .
1/
b100 -
b111 !
b111 )
1$
#547
0%
#550
0$
#555
1'
b101 -
0/
1$
#560
0$
#565
0"
0#
b101 .
1/
1$
#570
0$
#575
b10 +
0(
0'
b110 -
0/
1$
#580
0$
#585
1#
b110 .
1/
1$
#590
0$
#595
b0 +
b110 *
1'
b111 -
0/
1$
#600
0$
#605
1"
b111 .
1/
b110 !
b110 )
1$
#610
0$
#615
1(
b100 -
0/
1$
#620
0$
#625
0#
b100 .
1/
1$
#630
0$
#635
0'
b101 -
0/
1$
#640
0$
#645
0"
b101 .
1/
1$
#650
0$
#655
b10 +
0(
b110 -
0/
1$
#660
0$
#665
1#
b110 .
1/
1$
#670
0$
#675
b0 +
b101 *
1'
b111 -
0/
1$
#680
0$
#685
1"
b111 .
1/
b101 !
b101 )
1$
#690
0$
#695
1(
b100 -
0/
1$
#700
0$
#705
0#
b100 .
1/
1$
#710
0$
#715
0'
b101 -
0/
1$
#720
0$
#725
0"
b101 .
1/
1$
#730
0$
#735
b10 +
0(
b110 -
0/
1$
#740
0$
#745
1#
b110 .
1/
1$
#750
0$
#755
b0 +
b100 *
1'
b111 -
0/
1$
#760
0$
#765
1"
b111 .
1/
b100 !
b100 )
1$
#770
0$
#775
1(
b100 -
0/
1$
#780
0$
#785
0#
b100 .
1/
1$
#790
0$
#795
0'
b101 -
0/
1$
#800
0$
#805
0"
b101 .
1/
1$
#810
0$
#815
b10 +
0(
b110 -
0/
1$
#820
0$
#825
1#
b110 .
1/
1$
#830
0$
#835
b0 +
b11 *
1'
b111 -
0/
1$
#840
0$
#845
1"
b111 .
1/
b11 !
b11 )
1$
#850
0$
#855
1(
b100 -
0/
1$
#860
0$
#865
0#
b100 .
1/
1$
#870
0$
#875
0'
b101 -
0/
1$
#880
0$
#885
0"
b101 .
1/
1$
#890
0$
#895
b10 +
0(
b110 -
0/
1$
#900
0$
#905
1#
b110 .
1/
1$
#910
0$
#915
b0 +
b10 *
1'
b111 -
0/
1$
#920
0$
#925
1"
b111 .
1/
b10 !
b10 )
1$
#930
0$
#935
1(
b100 -
0/
1$
#940
0$
#945
0#
b100 .
1/
1$
#950
0$
#955
0'
b101 -
0/
1$
#960
0$
#965
0"
b101 .
1/
1$
#970
0$
#975
b10 +
0(
b110 -
0/
1$
#980
0$
#985
1#
b110 .
1/
1$
#990
0$
#995
b0 +
b1 *
1'
b111 -
0/
1$
#1000
0$
#1005
1"
b111 .
1/
b1 !
b1 )
1$
#1010
0$
#1015
1(
b100 -
0/
1$
#1020
0$
#1025
0#
b100 .
1/
1$
#1030
0$
#1035
0'
b101 -
0/
1$
#1040
0$
#1045
0"
b101 .
1/
1$
